{
  "dropdown": [
    {
      "content":"First item toggles left gutter",
      "class":"class",
      "id":"id",
      "xotype":"gutter-toggle",
      "xostate":"open",
      "xoobjectname":"left-gutter",
      "xoparent":"left-gutter"
    },
    {
      "content":"Second item toggles right gutter",
      "class":"class",
      "id":"id",
      "xotype":"gutter-toggle",
      "xostate":"open",
      "xoobjectname":"right-gutter",
      "xoparent":"right-gutter"
    },
    {
      "content":"Third item toggles modal",
      "class":"class",
      "id":"id",
      "xotype":"modal-toggle",
      "xostate":"open",
      "xoobjectname":"left-gutter",
      "xoparent":"parent"
    }
  ]
}